appunti/__init__.py
appunti/__main__.py
appunti/cli/__init__.py
appunti/cli/cli.py
appunti/cli/cli_config.py
appunti/cli/colors.py
appunti/cli/interactive_selection.py
appunti/cli/pager.py
appunti/cli/repl.py
appunti/parser/__init__.py
appunti/parser/parser.py
appunti/utils.py
appunti/wrappers/__init__.py
appunti/wrappers/base_wrapper.py
appunti/wrappers/editor_wrapper.py
appunti/wrappers/fzf_wrapper.py
appunti/wrappers/git_wrapper.py
appunti/zettelkasten/__init__.py
appunti/zettelkasten/notes.py
appunti/zettelkasten/sql.py
appunti/zettelkasten/zettelkasten.py
appunti-1.3.0.dist-info/LICENSE.md
appunti-1.3.0.dist-info/METADATA
appunti-1.3.0.dist-info/WHEEL
appunti-1.3.0.dist-info/entry_points.txt
appunti-1.3.0.dist-info/RECORD
