Metadata-Version: 2.1
Name: appunti
Version: 1.3.0
Summary: CLI program to manage your notes.
Author: Lorenzo Drumond
Author-email: drumondlorenzo@posteo.net
Requires-Python: >=3.11,<4.0
Classifier: Programming Language :: Python :: 3
Classifier: Programming Language :: Python :: 3.11
Classifier: Programming Language :: Python :: 3.12
